helpscout/__init__.py
helpscout/client.py
helpscout/exceptions.py
helpscout/model.py
helpscout/py.typed
python_helpscout-2.0.1.dist-info/LICENSE.md
python_helpscout-2.0.1.dist-info/METADATA
python_helpscout-2.0.1.dist-info/WHEEL
python_helpscout-2.0.1.dist-info/top_level.txt
python_helpscout-2.0.1.dist-info/RECORD
