Metadata-Version: 2.1
Name: python-helpscout
Version: 2.0.1
Summary: Wrapper to query Help Scout v2 API
License: MIT
Project-URL: homepage, https://github.com/C0rn3j/python-helpscout-v2
Classifier: License :: OSI Approved :: MIT License
Classifier: Programming Language :: Python :: 3
Classifier: Programming Language :: Python :: 3.11
Classifier: Programming Language :: Python :: 3.12
Classifier: Typing :: Typed
Requires-Python: >=3.11
License-File: LICENSE.md
Requires-Dist: requests~=2.31.0
